yucebio_scheduler/__init__.py
yucebio_scheduler/commands.py
yucebio_scheduler/scheduler.py
yucebio_scheduler/utils.py
yucebio_scheduler/jobs/__init__.py
yucebio_scheduler/jobs/example.py
yucebio_scheduler/rpc/__init__.py
yucebio_scheduler/rpc/client.py
yucebio_scheduler/rpc/server.py
yucebio_scheduler/web/__init__.py
yucebio_scheduler/web/api.py
yucebio_scheduler/web/django.py
yucebio_scheduler/web/flask.py
yucebio_scheduler/web/django_mongo/__init__.py
yucebio_scheduler/web/django_mongo/apps.py
yucebio_scheduler/web/django_mongo/urls.py
yucebio_scheduler/web/django_mongo/utils.py
yucebio_scheduler/web/django_mongo/views.py
yucebio_scheduler/web/django_mongo/management/__init__.py
yucebio_scheduler/web/django_mongo/management/commands/__init__.py
yucebio_scheduler/web/django_mongo/management/commands/scheduler.py
Yucebio_Scheduler-0.0.5.dist-info/METADATA
Yucebio_Scheduler-0.0.5.dist-info/WHEEL
Yucebio_Scheduler-0.0.5.dist-info/entry_points.txt
Yucebio_Scheduler-0.0.5.dist-info/top_level.txt
Yucebio_Scheduler-0.0.5.dist-info/RECORD
