Metadata-Version: 2.1
Name: Yucebio-Scheduler
Version: 0.0.5
Summary: 通用任务调度器-基于APScheduler实现
Home-page: UNKNOWN
Author: huangqingjun
Author-email: huangqingjun@yucebio.com
License: MIT
Platform: UNKNOWN
Classifier: License :: OSI Approved :: MIT License
Classifier: Programming Language :: Python
Classifier: Programming Language :: Python :: 3
Classifier: Programming Language :: Python :: 3.5
Classifier: Programming Language :: Python :: Implementation :: CPython
Classifier: Programming Language :: Python :: Implementation :: PyPy
Requires-Python: >=3.5
Requires-Dist: click (>=7.1.2)
Requires-Dist: icecream (>=2.1.0)
Requires-Dist: Yucebio-Config (>=0.0.2)
Requires-Dist: APScheduler (>=3.7.0)
Requires-Dist: rpyc (>=5.0.1)
Requires-Dist: SQLAlchemy (>=1.4.0)
Requires-Dist: python-dateutil (>=2.0.0)
Provides-Extra: django
Requires-Dist: psutil ; extra == 'django'
Requires-Dist: django ; extra == 'django'
